alsdac/__init__.py
alsdac/test.py
alsdac/caproto/__init__.py
alsdac/ophyd/__init__.py
alsdac/tests/__init__.py
alsdac-0.2.0.dist-info/METADATA
alsdac-0.2.0.dist-info/RECORD
alsdac-0.2.0.dist-info/WHEEL
alsdac-0.2.0.dist-info/top_level.txt
