Metadata-Version: 2.1
Name: alsdac
Version: 0.2.0
Summary: Python API over the ALS LabView Data Acquisition and Controls System TCP/IP commands
Home-page: https://github.com/ronpandolfi/alsdac
Author: Ronald J Pandolfi
Author-email: ronpandolfi@lbl.gov
License: BSD (3-clause)
Keywords: synchrotron controls beamline hardware data
Platform: UNKNOWN
Classifier: Development Status :: 3 - Alpha
Classifier: Intended Audience :: Science/Research
Classifier: Topic :: Scientific/Engineering :: Physics
Classifier: License :: OSI Approved :: BSD License
Classifier: Programming Language :: Python :: 3.6
Requires-Python: >=3.6
Requires-Dist: trio
Requires-Dist: numpy
